jtoolbox/__init__.py
jtoolbox/common_settings.py
jtoolbox/graph.py
jtoolbox/logger.py
jtoolbox/utils.py
joshuaeh_jtoolbox-0.0.1a0.dist-info/METADATA
joshuaeh_jtoolbox-0.0.1a0.dist-info/WHEEL
joshuaeh_jtoolbox-0.0.1a0.dist-info/licenses/LICENSE
joshuaeh_jtoolbox-0.0.1a0.dist-info/RECORD
