Metadata-Version: 2.4
Name: joshuaeh.jtoolbox
Version: 0.0.1a0
Summary: Shortcuts and utilities for things I often do
Project-URL: Homepage, https://github.com/joshuaeh/jtoolbox
Project-URL: Issues, https://github.com/joshuaeh/jtoolbox/issues
Author-email: Joshua Hammond <jhammond02@gmail.com>
License: MIT License
License-File: LICENSE
Classifier: License :: OSI Approved :: MIT License
Classifier: Operating System :: OS Independent
Classifier: Programming Language :: Python :: 3
Requires-Python: >=3.8
Requires-Dist: h5py
Requires-Dist: matplotlib
Requires-Dist: numpy
Requires-Dist: pandas
Requires-Dist: seaborn
